pyschema2/__init__.py
pyschema2/main.py
pyschema2-0.0.2.dist-info/LICENSE
pyschema2-0.0.2.dist-info/METADATA
pyschema2-0.0.2.dist-info/WHEEL
pyschema2-0.0.2.dist-info/top_level.txt
pyschema2-0.0.2.dist-info/RECORD
