Metadata-Version: 2.1
Name: pyschema2
Version: 0.0.2
Summary: Schema generation and validation for pyspark
Home-page: https://github.com/stonezhong/pyschema
Author: Stone Zhong
Author-email: stonezhong@hotmail.com
License: MIT
Platform: UNKNOWN
Classifier: License :: OSI Approved :: MIT License
Classifier: Programming Language :: Python :: 2
Classifier: Programming Language :: Python :: 3
Requires-Dist: pyspark
Requires-Dist: py-dateutil
Requires-Dist: jsonschema
